checkedid/__init__.py
checkedid/__main__.py
checkedid/client.py
checkedid/models/__init__.py
checkedid/models/base.py
checkedid/models/generated.py
checkedid/models/missing.py
checkedid/models/renamed.py
checkedid/py.typed
checkedid_python_client-0.1.2.dist-info/entry_points.txt
checkedid_python_client-0.1.2.dist-info/LICENSE
checkedid_python_client-0.1.2.dist-info/WHEEL
checkedid_python_client-0.1.2.dist-info/METADATA
checkedid_python_client-0.1.2.dist-info/RECORD
