Metadata-Version: 2.1
Name: checkedid-python-client
Version: 0.1.2
Summary: CheckedID Python API client
Home-page: https://github.com/foarsitter/checkedid-python-client
License: MIT
Author: Jelmer Draaijer
Author-email: jelmer.draaijer@dok.works.nl
Requires-Python: >=3.7,<4.0
Classifier: Development Status :: 4 - Beta
Classifier: License :: OSI Approved :: MIT License
Classifier: Programming Language :: Python :: 3
Classifier: Programming Language :: Python :: 3.10
Classifier: Programming Language :: Python :: 3.7
Classifier: Programming Language :: Python :: 3.8
Classifier: Programming Language :: Python :: 3.9
Requires-Dist: click (>=8.0.1)
Requires-Dist: httpx (>=0.23.1,<0.24.0)
Requires-Dist: pydantic (>=1.10.2,<2.0.0)
Project-URL: Changelog, https://github.com/foarsitter/checkedid-python-client/releases
Project-URL: Documentation, https://checkedid-python-client.readthedocs.io
Project-URL: Repository, https://github.com/foarsitter/checkedid-python-client
